Metadata-Version: 2.1
Name: sentry-14-dingding
Version: 1.0.0
Summary: A Sentry extension which send errors stats to DingDing
Home-page: https://github.com/cench/sentry-10-dingding
Author: season
Author-email: season2991@gmail.com
License: MIT
Keywords: sentry dingding
Platform: UNKNOWN
Classifier: Programming Language :: Python :: 2.7
Classifier: License :: OSI Approved :: MIT License
Requires-Dist: sentry>=9.0.0
Requires-Dist: requests
